mlni/__init__.py
mlni/adml_classification.py
mlni/adml_classification_nn.py
mlni/adml_regression.py
mlni/adml_regression_elastic.py
mlni/adml_regression_lasso.py
mlni/adml_regression_mlp.py
mlni/adml_regression_nn.py
mlni/adml_regression_rbf.py
mlni/base.py
mlni/classification.py
mlni/classification_nn.py
mlni/cli.py
mlni/clustering.py
mlni/hydra_clustering.py
mlni/main.py
mlni/regression.py
mlni/regression_elastic.py
mlni/regression_lasso.py
mlni/regression_mlp.py
mlni/regression_nn.py
mlni/regression_rbf.py
mlni/utils.py
mlni-0.1.5.1.dist-info/LICENSE
mlni-0.1.5.1.dist-info/METADATA
mlni-0.1.5.1.dist-info/WHEEL
mlni-0.1.5.1.dist-info/entry_points.txt
mlni-0.1.5.1.dist-info/top_level.txt
mlni-0.1.5.1.dist-info/RECORD
