Metadata-Version: 2.1
Name: mlni
Version: 0.1.5.1
Summary: Machine Learning in NeuroImaging for various tasks, e.g., regression, classification and clustering.
Home-page: https://github.com/anbai106/mlni
Author: junhao.wen
Author-email: junhao.wen89@email.com
Classifier: Programming Language :: Python :: 3
Classifier: License :: OSI Approved :: MIT License
Classifier: Operating System :: OS Independent
License-File: LICENSE
